LICENSE
MANIFEST.in
README.md
requirements.txt
setup.py
shams/__init__.py
shams/factory.py
shams/primitives.py
shams.egg-info/PKG-INFO
shams.egg-info/SOURCES.txt
shams.egg-info/dependency_links.txt
shams.egg-info/not-zip-safe
shams.egg-info/requires.txt
shams.egg-info/top_level.txt