Metadata-Version: 1.1
Name: shams
Version: 0.0.2
Summary: A Python library for generating fake data
Home-page: https://github.com/dgouldin/python-shams
Author: David Gouldin
Author-email: david@gould.in
License: Copyright (c) 2014 David Gouldin
